Missingvalues/__init__.py
Missingvalues/missingValuesVivek.py
vkhanduja_101703624-0.0.3.dist-info/LICENSE.txt
vkhanduja_101703624-0.0.3.dist-info/METADATA
vkhanduja_101703624-0.0.3.dist-info/WHEEL
vkhanduja_101703624-0.0.3.dist-info/entry_points.txt
vkhanduja_101703624-0.0.3.dist-info/top_level.txt
vkhanduja_101703624-0.0.3.dist-info/RECORD
